soato/__init__.py
soato/admin.py
soato/apps.py
soato/models.py
soato/serializers.py
soato/tasks.py
soato/urls.py
soato/urls_api.py
soato/views.py
soato/views_api.py
soato/fixtures/__init__.py
soato/fixtures/soato.json
soato/management/__init__.py
soato/management/commands/__init__.py
soato/management/commands/soato.py
soato/migrations/0001_initial.py
soato/migrations/0002_auto_20210415_1741.py
soato/migrations/__init__.py
soato/static/css/soato.css
soato/static/js/soato.js
soato/templates/soato/base.html
soato/templates/soato/city_detail.html
soato/templates/soato/city_list.html
soato/templates/soato/country_detail.html
soato/templates/soato/country_list.html
soato/templates/soato/district_detail.html
soato/templates/soato/district_list.html
soato/templates/soato/region_detail.html
soato/templates/soato/region_list.html
uzsoato_registry-0.1.1.dist-info/AUTHORS.rst
uzsoato_registry-0.1.1.dist-info/LICENSE
uzsoato_registry-0.1.1.dist-info/METADATA
uzsoato_registry-0.1.1.dist-info/WHEEL
uzsoato_registry-0.1.1.dist-info/top_level.txt
uzsoato_registry-0.1.1.dist-info/RECORD
