Metadata-Version: 2.1
Name: uzsoato-registry
Version: 0.1.1
Summary: SOATO Registry of Uzbekistan
Home-page: https://github.com/dcopm999/uzsoato_registry
Author: Pavel Tanchev
Author-email: dcopm999@gmail.com
License: MIT
Keywords: Uzbekistan,SOATO,address,registry
Platform: UNKNOWN
Classifier: Development Status :: 3 - Alpha
Classifier: Framework :: Django :: 2.1
Classifier: Framework :: Django :: 2.2
Classifier: Framework :: Django :: 3.0
Classifier: Framework :: Django :: 3.1
Classifier: Framework :: Django :: 3.2
Classifier: Intended Audience :: Developers
Classifier: License :: OSI Approved :: BSD License
Classifier: Natural Language :: English
Classifier: Programming Language :: Python :: 3
Classifier: Programming Language :: Python :: 3.7
Classifier: Programming Language :: Python :: 3.8
Classifier: Programming Language :: Python :: 3.9
Requires-Dist: Django (<3.3,>=2.2.20,>=3.0.14,>=3.1.8,>=3.2)
Requires-Dist: djangorestframework
Requires-Dist: django-celery-beat
Requires-Dist: celery
Requires-Dist: pytils
Requires-Dist: redis
Requires-Dist: wget
Requires-Dist: openpyxl
